AUTHORS.rst
CONTRIBUTING.rst
HISTORY.rst
LICENSE
MANIFEST.in
README.rst
config_handler.py
setup.cfg
setup.py
config_handle.egg-info/PKG-INFO
config_handle.egg-info/SOURCES.txt
config_handle.egg-info/dependency_links.txt
config_handle.egg-info/not-zip-safe
config_handle.egg-info/pbr.json
config_handle.egg-info/top_level.txt
docs/Makefile
docs/authors.rst
docs/conf.py
docs/contributing.rst
docs/history.rst
docs/index.rst
docs/installation.rst
docs/make.bat
docs/readme.rst
docs/usage.rst
tests/__init__.py
tests/test_config-handle.py