Metadata-Version: 1.1
Name: config-handle
Version: 0.2.1
Summary: Get a handle on configuration files
Home-page: https://github.com/iansmcf/config-handle
Author: Ian McFarlane
Author-email: iansmcfarlane@gmail.com
License: BSD
Keywords: config-handle
Platform: UNKNOWN
Classifier: Development Status :: 2 - Pre-Alpha
Classifier: Intended Audience :: Developers
Classifier: License :: OSI Approved :: BSD License
Classifier: Natural Language :: English
Classifier: Programming Language :: Python :: 2.7
